opswrapper/__init__.py
opswrapper/__version__
opswrapper/algorithm.py
opswrapper/analysis.py
opswrapper/base.py
opswrapper/config.py
opswrapper/constraints.py
opswrapper/element.py
opswrapper/formatting.py
opswrapper/integration.py
opswrapper/integrator.py
opswrapper/material.py
opswrapper/model.py
opswrapper/output.py
opswrapper/section.py
opswrapper/test.py
opswrapper/uniaxialmaterialanalysis.py
opswrapper/utils.py
opswrapper-5.2.0.dist-info/LICENSE.txt
opswrapper-5.2.0.dist-info/METADATA
opswrapper-5.2.0.dist-info/WHEEL
opswrapper-5.2.0.dist-info/top_level.txt
opswrapper-5.2.0.dist-info/RECORD
