Metadata-Version: 2.1
Name: opswrapper
Version: 5.2.0
Summary: Python helpers for writing OpenSees scripts.
Home-page: https://github.com/otaithleigh/opswrapper
Author: Peter Talley
Author-email: ptalley2@vols.utk.edu
License: MIT
Classifier: License :: OSI Approved :: MIT License
Classifier: Operating System :: OS Independent
Classifier: Programming Language :: Python :: 3
Classifier: Topic :: Scientific/Engineering
Requires-Python: >=3.7
License-File: LICENSE.txt
Requires-Dist: numpy
Requires-Dist: tomli
Requires-Dist: xarray
